plams-2025.104.data/scripts/plams
plams-2025.104.dist-info/licenses/LICENSE.md
scm/plams/.flake8
scm/plams/__init__.py
scm/plams/setup.py
scm/plams/version.py
scm/plams/core/__init__.py
scm/plams/core/basejob.py
scm/plams/core/enums.py
scm/plams/core/errors.py
scm/plams/core/formatters.py
scm/plams/core/functions.py
scm/plams/core/jobmanager.py
scm/plams/core/jobrunner.py
scm/plams/core/logging.py
scm/plams/core/private.py
scm/plams/core/results.py
scm/plams/core/settings.py
scm/plams/core/threading_utils.py
scm/plams/examples/BAND_NiO_HubbardU.py
scm/plams/examples/ConvertToAMSRKFTrajectory.py
scm/plams/examples/CustomASECalculator.py
scm/plams/examples/MoleculesFromRKFTrajectory.py
scm/plams/examples/MoleculesTable.py
scm/plams/examples/QE_AMS_AFM_HubbardU.py
scm/plams/examples/README.md
scm/plams/examples/ReactionEnergyBenchmark.py
scm/plams/examples/ReductionOxidationPotentials.py
scm/plams/examples/SellaTransitionStateSearch.py
scm/plams/examples/ams_crs.py
scm/plams/examples/ams_pyCRS.py
scm/plams/examples/balance_equations.py
scm/plams/examples/generate_example.sh
scm/plams/examples/get_hbonds.py
scm/plams/examples/get_irspectrum.py
scm/plams/examples/get_water_indices.py
scm/plams/examples/molecules_ReactionEnergyBenchmark.zip
scm/plams/examples/nbconvert_utils.py
scm/plams/examples/numgrad.py
scm/plams/examples/rkf_to_wrapped_dcd.py
scm/plams/examples/ADFFrag/adffrag.ipynb
scm/plams/examples/ADFFrag/adffrag.py
scm/plams/examples/ADFFrag/butadiene.xyz
scm/plams/examples/ADFFrag/ethene.xyz
scm/plams/examples/ADFNBO/ADFNBO.ipynb
scm/plams/examples/ADFNBO/ADFNBO.py
scm/plams/examples/ADFVibronicDOS/ADFVibronicDOS.ipynb
scm/plams/examples/ADFVibronicDOS/ADFVibronicDOS.py
scm/plams/examples/AMSPlumedMD/ams_plumed.ipynb
scm/plams/examples/AMSPlumedMD/ams_plumed.py
scm/plams/examples/AMSSettingsInput/ams_settings_input.ipynb
scm/plams/examples/AMSSettingsInput/ams_settings_input.py
scm/plams/examples/AMSSettingsSystem/ams_settings_system.ipynb
scm/plams/examples/AMSSettingsSystem/ams_settings_system.py
plams-2025.104.dist-info/METADATA
plams-2025.104.dist-info/WHEEL
plams-2025.104.dist-info/top_level.txt
plams-2025.104.dist-info/RECORD
