Metadata-Version: 2.4
Name: plams
Version: 2025.104
Summary: Python Library for Automating Molecular Simulations
Author-email: Software for Chemistry and Materials <info@scm.com>
Maintainer-email: Software for Chemistry and Materials <info@scm.com>
License: LGPLv3
Project-URL: Homepage, https://www.scm.com/doc/plams/
Project-URL: Documentation, https://www.scm.com/doc/plams/
Project-URL: GitHub, https://github.com/SCM-NV/PLAMS/
Project-URL: Changelog, https://github.com/SCM-NV/PLAMS/blob/trunk/CHANGELOG.md
Keywords: molecular modeling,computational chemistry,workflow
Classifier: License :: OSI Approved :: GNU Lesser General Public License v3 (LGPLv3)
Classifier: Development Status :: 5 - Production/Stable
Classifier: Intended Audience :: Science/Research
Classifier: Operating System :: OS Independent
Classifier: Programming Language :: Python
Classifier: Programming Language :: Python :: 3 :: Only
Classifier: Programming Language :: Python :: 3.8
Classifier: Programming Language :: Python :: 3.9
Classifier: Programming Language :: Python :: 3.10
Classifier: Programming Language :: Python :: 3.11
Classifier: Programming Language :: Python :: 3.12
Classifier: Programming Language :: Python :: 3.13
Classifier: Topic :: Scientific/Engineering :: Chemistry
Classifier: Topic :: Scientific/Engineering :: Physics
Classifier: Topic :: Scientific/Engineering :: Bio-Informatics
Classifier: Topic :: Software Development :: Libraries :: Python Modules
Requires-Python: >=3.8
License-File: LICENSE.md
Requires-Dist: numpy>=1.21.2
Requires-Dist: dill>=0.3.6
Provides-Extra: chem
Requires-Dist: rdkit>=2017; extra == "chem"
Requires-Dist: ase>=3.18; extra == "chem"
Provides-Extra: ams
Requires-Dist: psutil>=5.8.0; extra == "ams"
Requires-Dist: py-ubjson>=0.16.1; extra == "ams"
Requires-Dist: watchdog>=2.1.8; extra == "ams"
Provides-Extra: analysis
Requires-Dist: scipy>=1.8.0; extra == "analysis"
Requires-Dist: matplotlib>=3.5.1; extra == "analysis"
Requires-Dist: pandas>=1.5.2; extra == "analysis"
Requires-Dist: networkx>=2.7.1; extra == "analysis"
Requires-Dist: natsort>=8.1.0; extra == "analysis"
Requires-Dist: h5py>=3.6.0; extra == "analysis"
Requires-Dist: ipython>=7.22.0; extra == "analysis"
Provides-Extra: docs
Requires-Dist: sphinx<8.2,>=6.2.1; extra == "docs"
Requires-Dist: sphinx_copybutton>=0.5.2; extra == "docs"
Requires-Dist: sphinx_design>=0.5.0; extra == "docs"
Requires-Dist: ipython>=7.22.0; extra == "docs"
Provides-Extra: examples
Requires-Dist: jupyterlab>=3.5.2; extra == "examples"
Provides-Extra: dev
Requires-Dist: pytest>=7.4.0; extra == "dev"
Requires-Dist: coverage>=7.5.3; extra == "dev"
Requires-Dist: black==24.8.0; extra == "dev"
Requires-Dist: black[jupyter]==24.8.0; extra == "dev"
Requires-Dist: flake8==5.0.4; extra == "dev"
Requires-Dist: mypy==1.12.0; extra == "dev"
Dynamic: license-file
